{
  "species:cruncher_egg": 3,
  "species:wicked_swapper": 3,
  "species:springling_egg": 3,
  "species:frozen_hair": 3,
  "species:cranktrap": 3,
  "species:birt_egg": 3,
  "species:broken_links": 2,
  "species:birtday_cake": 3,
  "species:hopelight": 2,
  "species:ichor_bottle": 4,
  "species:wicked_wax": 2,
  "species:cracked_wraptor_egg": 3,
  "species:coil": 2,
  "species:ricoshield": 4,
  "species:ghoul_tongue": 2,
  "species:wicked_mask": 3,
  "species:wraptor_egg": 3,
  "species:cruncher_pellet": 3,
  "species:kinetic_core": 4,
  "species:frozen_meat": 4,
  "species:wicked_dope": 3,
  "species:werefang": 2,
  "species:deepfish_bucket": 3,
  "species:monster_meal": 2,
  "species:chaindelier": 2,
  "species:birtday_cake_slice": 2,
  "species:petrified_egg": 3,
  "species:speclight": 2,
  "species:crankbow": 3,
  "species:harpoon": 2,
  "species:smoke_bomb": 3,
  "species:wicked_treat": 3,
  "species:deflector_dummy": 4,
  "species:youth_potion": 5
}